skald/__init__.py
skald/cli.py
skald/enums.py
skald/exceptions.py
skald/tui.py
skald/tui.tcss
skald/utils.py
skald-0.7.0.dist-info/entry_points.txt
skald-0.7.0.dist-info/LICENSE
skald-0.7.0.dist-info/METADATA
skald-0.7.0.dist-info/WHEEL
skald-0.7.0.dist-info/RECORD
