Metadata-Version: 2.3
Name: skald
Version: 0.7.0
Summary: 📟 a simple and efficient experiment logger for Python 🐍
Home-page: https://github.com/laurenzbeck/skald
License: MIT
Keywords: logging,tui
Author: Laurenz Farthofer
Author-email: laurenz@hey.com
Requires-Python: >=3.11,<4.0
Classifier: License :: OSI Approved :: MIT License
Classifier: Programming Language :: Python :: 3
Classifier: Programming Language :: Python :: 3.11
Classifier: Programming Language :: Python :: 3.12
Classifier: Programming Language :: Python :: 3.13
Requires-Dist: aiofile (>=3.8.8,<4.0.0)
Requires-Dist: loguru (>=0.7,<0.8)
Requires-Dist: matplotlib (>=3.9,<4.0)
Requires-Dist: pandas (>=2,<3)
Requires-Dist: polars (>=1,<2)
Requires-Dist: rich (>=13.7)
Requires-Dist: textual (>=0.76,<0.77)
Requires-Dist: textual-dev (>=1.5,<2.0)
Requires-Dist: textual-plotext (>=0.2,<0.3)
Requires-Dist: typer (>=0.12)
Project-URL: Repository, https://github.com/laurenzbeck/skald
